<PAMDataset>
  <PAMRasterBand band="1">
    <Histograms>
      <HistItem>
        <HistMin>-727.5859375</HistMin>
        <HistMax>1566.517333984375</HistMax>
        <BucketCount>256</BucketCount>
        <IncludeOutOfRange>1</IncludeOutOfRange>
        <Approximate>0</Approximate>
        <HistCounts>1|0|0|0|0|0|0|2|2|0|0|0|0|0|1|1|0|0|0|1|0|2|4|0|2|3|0|2|4|6|5|7|4|1|7|11|6|13|9|14|15|19|24|21|23|28|37|27|38|34|48|53|62|66|78|84|117|145|170|241|369|484|601|734|961|1209|1707|1808|2124|2672|3277|4067|5251|6685|7516|8455|8966|9497|10661|12124|12549|11570|9431|8989|8539|8252|7647|7041|7033|6971|5746|4849|4653|4539|4392|3988|3843|3665|3462|3533|3114|2913|2892|2584|2534|2406|2494|2356|2435|2340|2191|2223|2262|2236|2138|2172|2135|2064|2162|2148|2058|2216|2063|2013|1940|2091|1993|1814|1685|1531|1510|1365|1227|1132|1122|1051|1003|864|744|661|575|486|423|403|321|312|244|236|233|205|187|169|154|161|152|111|111|78|63|54|45|40|32|34|39|37|25|34|35|26|23|20|19|12|18|14|23|13|9|11|9|10|9|9|8|10|6|8|9|7|12|2|5|2|7|6|4|3|2|3|3|5|1|1|4|3|1|1|2|8|1|2|3|2|3|2|1|3|0|5|2|0|2|1|0|3|0|1|0|1|3|1|1|0|0|1|1|0|0|0|0|0|2|0|1|0|0|4|0|0|0|0|0|0|0|1</HistCounts>
      </HistItem>
    </Histograms>
    <Metadata>
      <MDI key="RepresentationType">ATHEMATIC</MDI>
      <MDI key="STATISTICS_COVARIANCES">29962.74042196719</MDI>
      <MDI key="STATISTICS_EXCLUDEDVALUES"></MDI>
      <MDI key="STATISTICS_MAXIMUM">1566.5173339844</MDI>
      <MDI key="STATISTICS_MEAN">102.39942473176</MDI>
      <MDI key="STATISTICS_MINIMUM">-727.5859375</MDI>
      <MDI key="STATISTICS_SKIPFACTORX">1</MDI>
      <MDI key="STATISTICS_SKIPFACTORY">1</MDI>
      <MDI key="STATISTICS_STDDEV">173.09748820236</MDI>
    </Metadata>
  </PAMRasterBand>
</PAMDataset>
