<PAMDataset>
  <PAMRasterBand band="1">
    <Histograms>
      <HistItem>
        <HistMin>-891.8360595703125</HistMin>
        <HistMax>1819.41650390625</HistMax>
        <BucketCount>256</BucketCount>
        <IncludeOutOfRange>1</IncludeOutOfRange>
        <Approximate>0</Approximate>
        <HistCounts>1|1|0|0|2|1|1|0|0|1|1|0|0|3|0|0|3|1|0|1|0|3|1|9|5|4|7|8|11|26|13|20|26|30|36|57|57|67|74|65|84|85|75|92|91|80|98|116|129|150|255|302|293|328|408|484|565|726|963|914|931|1322|1408|1892|1904|1920|2069|2246|2233|2360|2586|2686|3071|3734|4450|5533|6807|8824|10651|12176|13292|14287|15408|15685|14515|13362|11843|10841|10089|9415|9418|8116|7129|6310|5399|4658|3868|3158|2984|2880|2635|2417|2237|2127|2171|2042|1961|1945|1882|1631|1504|1446|1283|1212|1189|1072|936|726|635|535|435|399|341|307|248|264|240|188|128|117|91|78|69|76|78|80|65|67|56|55|61|50|53|50|46|45|41|32|49|47|35|38|41|38|28|35|30|34|34|21|27|25|27|24|27|13|18|21|17|25|9|11|18|18|16|16|11|13|8|8|11|8|8|7|12|12|7|5|5|10|6|7|5|10|6|8|3|5|8|3|7|3|5|3|4|7|3|2|2|5|0|0|4|4|1|3|3|1|2|0|0|0|0|1|1|2|0|1|1|0|0|0|0|0|0|0|0|1|0|0|0|0|0|0|0|0|0|0|0|0|0|0|0|0|0|1</HistCounts>
      </HistItem>
    </Histograms>
    <Metadata>
      <MDI key="RepresentationType">ATHEMATIC</MDI>
      <MDI key="STATISTICS_COVARIANCES">20769.08025437728</MDI>
      <MDI key="STATISTICS_EXCLUDEDVALUES"></MDI>
      <MDI key="STATISTICS_MAXIMUM">1819.4165039063</MDI>
      <MDI key="STATISTICS_MEAN">22.621645928411</MDI>
      <MDI key="STATISTICS_MINIMUM">-891.83605957031</MDI>
      <MDI key="STATISTICS_SKIPFACTORX">1</MDI>
      <MDI key="STATISTICS_SKIPFACTORY">1</MDI>
      <MDI key="STATISTICS_STDDEV">144.11481622088</MDI>
    </Metadata>
  </PAMRasterBand>
</PAMDataset>
